django_hibp.py
django_hibp-1.0.dist-info/LICENCE.md
django_hibp-1.0.dist-info/METADATA
django_hibp-1.0.dist-info/WHEEL
django_hibp-1.0.dist-info/top_level.txt
django_hibp-1.0.dist-info/RECORD
